abs_auth/__init__.py
abs_auth/auth_functions.py
abs_auth/jwt_functions.py
abs_auth/middleware.py
abs_auth_core-0.1.4.dist-info/METADATA
abs_auth_core-0.1.4.dist-info/WHEEL
abs_auth_core-0.1.4.dist-info/RECORD
