Metadata-Version: 2.3
Name: abs-auth-core
Version: 0.1.4
Summary: Authentication core utilities including JWT token management.
License: MIT
Author: AutoBridgeSystems
Author-email: info@autobridgesystems.com
Requires-Python: >=3.13,<4.0
Classifier: License :: OSI Approved :: MIT License
Classifier: Programming Language :: Python :: 3
Classifier: Programming Language :: Python :: 3.13
Requires-Dist: abs-exception-core (>=0.1.0,<0.2.0)
Requires-Dist: fastapi[standard] (>=0.115.12,<0.116.0)
Requires-Dist: passlib (>=1.7.4,<2.0.0)
Requires-Dist: pyjwt (>=2.10.1,<3.0.0)
